llm_kira/__init__.py
llm_kira/client/Optimizer.py
llm_kira/client/__init__.py
llm_kira/client/agent.py
llm_kira/client/anchor.py
llm_kira/client/enhance.py
llm_kira/client/llms/__init__.py
llm_kira/client/llms/base.py
llm_kira/client/llms/chatgpt.py
llm_kira/client/llms/openai.py
llm_kira/client/module/__init__.py
llm_kira/client/module/main.py
llm_kira/client/module/nlp_tool.py
llm_kira/client/module/platform.py
llm_kira/client/module/plugin/__init__.py
llm_kira/client/module/plugin/details.py
llm_kira/client/module/plugin/time.py
llm_kira/client/module/plugin/week.py
llm_kira/client/test/pot.py
llm_kira/client/test/test_module.py
llm_kira/client/types.py
llm_kira/client/vocab.json
llm_kira/creator/__init__.py
llm_kira/creator/base.py
llm_kira/creator/engine.py
llm_kira/creator/think.py
llm_kira/error.py
llm_kira/radio/__init__.py
llm_kira/radio/anchor.py
llm_kira/radio/crawer.py
llm_kira/radio/decomposer.py
llm_kira/radio/setting.py
llm_kira/requirements.txt
llm_kira/tool/__init__.py
llm_kira/tool/openai/__init__.py
llm_kira/tool/openai/api/__init__.py
llm_kira/tool/openai/api/api_url.json
llm_kira/tool/openai/api/api_utils.py
llm_kira/tool/openai/api/network.py
llm_kira/tool/openai/resouce/__init__.py
llm_kira/tool/openai/resouce/chat.py
llm_kira/tool/openai/resouce/completion.py
llm_kira/tool/openai/resouce/moderations.py
llm_kira/utils/api/LICENSE
llm_kira/utils/api/README.md
llm_kira/utils/api/__init__.py
llm_kira/utils/api/data/apple.png
llm_kira/utils/api/data/map.png
llm_kira/utils/api/data/simfang.ttf
llm_kira/utils/api/data/stop_words.txt
llm_kira/utils/api/data/synonym.json
llm_kira/utils/api/keyphrase/__init__.py
llm_kira/utils/api/keyphrase/keyphrase.py
llm_kira/utils/api/keywords/__init__.py
llm_kira/utils/api/keywords/textrank.py
llm_kira/utils/api/keywords/tfidf.py
llm_kira/utils/api/sentiment/__init__.py
llm_kira/utils/api/sentiment/data/degreeDict.json
llm_kira/utils/api/sentiment/data/jieba.dic
llm_kira/utils/api/sentiment/data/notDict.json
llm_kira-0.7.4.dist-info/LICENSE
llm_kira-0.7.4.dist-info/METADATA
llm_kira-0.7.4.dist-info/WHEEL
llm_kira-0.7.4.dist-info/RECORD
