Metadata-Version: 2.1
Name: llm-kira
Version: 0.7.4
Summary: chatbot client for llm
Home-page: https://github.com/sudoskys/llm_kira
License: LGPL-2.1-or-later
Author: sudoskys
Author-email: coldlando@hotmail.com
Maintainer: sudoskys
Maintainer-email: coldlando@hotmail.com
Requires-Python: >=3.8,<4.0
Classifier: License :: OSI Approved
Classifier: Programming Language :: Python :: 3
Classifier: Programming Language :: Python :: 3.8
Classifier: Programming Language :: Python :: 3.9
Classifier: Programming Language :: Python :: 3.10
Classifier: Programming Language :: Python :: 3.11
Requires-Dist: aiohttp (>=3.8.3,<4.0.0)
Requires-Dist: beautifulsoup4 (>=4.11.1,<5.0.0)
Requires-Dist: duckduckgo-search (==2.8.0)
Requires-Dist: elara (>=0.5.4,<0.6.0)
Requires-Dist: fasttext-wheel (>=0.9.2,<0.10.0)
Requires-Dist: goose3 (>=3.1.12,<4.0.0)
Requires-Dist: httpx (>=0.23.1,<0.24.0)
Requires-Dist: inscriptis (>=2.3.2,<3.0.0)
Requires-Dist: jieba (>=0.42.1,<0.43.0)
Requires-Dist: loguru (>=0.6.0,<0.7.0)
Requires-Dist: nltk (>=3.8,<4.0)
Requires-Dist: numpy (>=1.22.1,<2.0.0)
Requires-Dist: openai (>=0.26.5,<0.27.0)
Requires-Dist: openai-async (>=0.0.2,<0.0.3)
Requires-Dist: pillow (>=9.3.0,<10.0.0)
Requires-Dist: pydantic (>=1.10.4,<2.0.0)
Requires-Dist: redis (>=4.4.0,<5.0.0)
Requires-Dist: shortuuid (>=1.0.11,<2.0.0)
Requires-Dist: similarities (>=1.0.4,<2.0.0)
Requires-Dist: tenacity (>=8.2.0,<9.0.0)
Requires-Dist: tiktoken (>=0.1.2,<0.2.0)
Project-URL: Repository, https://github.com/sudoskys/llm_kira
